BigM/BigM.py
BigM/InputHandling.py
BigM/__init__.py
BigM/aliases.py
BigM/analyse.py
BigM/graph.py
BigM/simplex.py
BigM/utilities.py
BigM-0.0.0.dist-info/LICENCE
BigM-0.0.0.dist-info/METADATA
BigM-0.0.0.dist-info/WHEEL
BigM-0.0.0.dist-info/top_level.txt
BigM-0.0.0.dist-info/RECORD
